RaPLibs/ConfigFile.py
RaPLibs/GetBits.py
RaPLibs/Hex_To_Bit_Converter.py
RaPLibs/NistTest.py
RaPLibs/RaPLib.py
RaPLibs/__init__.py
RaPLibs/flash_function.py
raplibs_f10-0.8.dist-info/LICENSE
raplibs_f10-0.8.dist-info/METADATA
raplibs_f10-0.8.dist-info/WHEEL
raplibs_f10-0.8.dist-info/top_level.txt
raplibs_f10-0.8.dist-info/RECORD
